<operation>
		<operationName myvalue="ifMultiple"/>
		<ifConditionMultiple myvalue="and">
			
			<ifConditionBasic>
				<key myvalue="PsList-PID"/>
				<value myvalue="1088"/>
				<collection myvalue="PsListCollection"/>
				<operator myvalue="contains"/>
			</ifConditionBasic>

			<ifConditionBasic>
				<key myvalue="PsList-PID"/>
				<value myvalue="10881"/>
				<collection myvalue="PsListCollection"/>
				<operator myvalue="contains"/>
			</ifConditionBasic>

			
		</ifConditionMultiple>
	</operation>